flink_connector_compress/__init__.py
flink_connector_compress/compress.py
flink_connector_compress-0.1.0.dist-info/LICENSE
flink_connector_compress-0.1.0.dist-info/METADATA
flink_connector_compress-0.1.0.dist-info/WHEEL
flink_connector_compress-0.1.0.dist-info/top_level.txt
flink_connector_compress-0.1.0.dist-info/RECORD
