Metadata-Version: 2.1
Name: flink-connector-compress
Version: 0.1.0
Summary: A small wrapper library around Java API for writing compressed bulk file sinks.
Author: "Bartosz Mikulski"
Author-email: Bartosz Mikulski <bartosz.mikulski@deep.bi>
License: Apache-2.0
Project-URL: Homepage, https://github.com/deep-bi/flink-connector-compress
Project-URL: Bug Tracker, https://github.com/deep-bi/flink-connector-compress/issues
Classifier: Programming Language :: Python :: 3
Classifier: License :: OSI Approved :: MIT License
Classifier: Operating System :: OS Independent
Requires-Python: >=3.7
License-File: LICENSE
Requires-Dist: apache-flink (>=1.15)
